powerboard/demo.py
powerboard/libipmi.py
powerboard/metadata.py
powerboard/plugin.py
powerboard/profiling_example.py
powerboard/summary_v2.py
powerboard/static/Chart.min.css
powerboard/static/Chart.min.js
powerboard/static/index.js
powerboard-0.0.1.dist-info/METADATA
powerboard-0.0.1.dist-info/WHEEL
powerboard-0.0.1.dist-info/entry_points.txt
powerboard-0.0.1.dist-info/top_level.txt
powerboard-0.0.1.dist-info/RECORD
