Metadata-Version: 2.1
Name: powerboard
Version: 0.0.1
Summary: Energy Profiling plugin for TensorBoard.
Home-page: https://github.com/Unicamp-OpenPower/PowerBoard
Author: MatheusCod, juliokiyoshi
Author-email: openpower@ic.unicamp.br
License: UNKNOWN
Project-URL: Bug Tracker, https://github.com/Unicamp-OpenPower/PowerBoard/issues
Platform: UNKNOWN
Classifier: Programming Language :: Python :: 3
Classifier: License :: OSI Approved :: Apache Software License
Classifier: Operating System :: POSIX :: Linux
